[
  {
    "text": "How much would the San Juan trip cost, for economy class?",
    "intentName": "None",
    "entityLabels": [
      {
        "entityName": "dst_city",
        "startCharIndex": 19,
        "endCharIndex": 27
      }
    ]
  },
  {
    "text": "Please book that one!",
    "intentName": "book",
    "entityLabels": []
  },
  {
    "text": "Thank you!",
    "intentName": "None",
    "entityLabels": []
  },
  {
    "text": "Hi!",
    "intentName": "None",
    "entityLabels": []
  },
  {
    "text": "HAve 2500 to try to get to my internship. Need to leave Phoenix between September 8 and 17. Could that get me tickets to Kingston?",
    "intentName": "book",
    "entityLabels": [
      {
        "entityName": "budget",
        "startCharIndex": 5,
        "endCharIndex": 9
      },
      {
        "entityName": "or_city",
        "startCharIndex": 56,
        "endCharIndex": 63
      },
      {
        "entityName": "str_date",
        "startCharIndex": 72,
        "endCharIndex": 83
      },
      {
        "entityName": "end_date",
        "startCharIndex": 88,
        "endCharIndex": 90
      },
      {
        "entityName": "dst_city",
        "startCharIndex": 121,
        "endCharIndex": 129
      }
    ]
  },
  {
    "text": "how much would 9 days cost me?",
    "intentName": "None",
    "entityLabels": []
  },
  {
    "text": "Could you get me to Houston for cheaper?",
    "intentName": "None",
    "entityLabels": [
      {
        "entityName": "dst_city",
        "startCharIndex": 20,
        "endCharIndex": 27
      }
    ]
  },
  {
    "text": "How cheap?",
    "intentName": "None",
    "entityLabels": []
  },
  {
    "text": "But while we're at it, can we also look into Recife?",
    "intentName": "None",
    "entityLabels": [
      {
        "entityName": "dst_city",
        "startCharIndex": 45,
        "endCharIndex": 51
      }
    ]
  },
  {
    "text": "Can you tell me more about the hotel in Houston? My mother gets worried whenever I have to travel, she likes me to have breakfast for some reason",
    "intentName": "None",
    "entityLabels": [
      {
        "entityName": "dst_city",
        "startCharIndex": 40,
        "endCharIndex": 47
      }
    ]
  },
  {
    "text": "And the name of the hotel?",
    "intentName": "None",
    "entityLabels": []
  },
  {
    "text": "Yes!!",
    "intentName": "None",
    "entityLabels": []
  },
  {
    "text": ":+1:",
    "intentName": "None",
    "entityLabels": []
  },
  {
    "text": "I have $3300 and I\u2019d like to take my 6 darling little grandchildren on a cute little getaway to Salvador from Minneapolis.",
    "intentName": "book",
    "entityLabels": [
      {
        "entityName": "budget",
        "startCharIndex": 7,
        "endCharIndex": 12
      },
      {
        "entityName": "dst_city",
        "startCharIndex": 96,
        "endCharIndex": 104
      },
      {
        "entityName": "or_city",
        "startCharIndex": 110,
        "endCharIndex": 121
      }
    ]
  },
  {
    "text": "Well are there any trips to Tampa?",
    "intentName": "None",
    "entityLabels": [
      {
        "entityName": "dst_city",
        "startCharIndex": 28,
        "endCharIndex": 33
      }
    ]
  },
  {
    "text": "Any trips to las vegas?",
    "intentName": "None",
    "entityLabels": [
      {
        "entityName": "dst_city",
        "startCharIndex": 13,
        "endCharIndex": 22
      }
    ]
  },
  {
    "text": "What rating is the hotel? And my grandchildren want to know if they have whyfly? I dont know what whyfly is but they said they have to have it for their weird looking devices.",
    "intentName": "None",
    "entityLabels": []
  },
  {
    "text": "Ok, well i think that sounds about right! Thank you, we would like to book this one, the grandkids are already so flabbergasted, the little buggers can\u2019t wait! How much does this cost?",
    "intentName": "None",
    "entityLabels": []
  },
  {
    "text": "Lovely! When does this trip leave and come back?",
    "intentName": "None",
    "entityLabels": []
  },
  {
    "text": "Oh no! That just wont do. The little ones dont get back from summer camp unitl the 6th and school starts on the 21st. Is there a trip between those dates?",
    "intentName": "None",
    "entityLabels": [
      {
        "entityName": "str_date",
        "startCharIndex": 83,
        "endCharIndex": 86
      },
      {
        "entityName": "end_date",
        "startCharIndex": 112,
        "endCharIndex": 116
      }
    ]
  },
  {
    "text": "i have 12 days for vacay",
    "intentName": "book",
    "entityLabels": []
  },
  {
    "text": "i dont know, was hoping you could help me decide. i live in Kingston and i want to travel on or after the 8th",
    "intentName": "None",
    "entityLabels": [
      {
        "entityName": "or_city",
        "startCharIndex": 60,
        "endCharIndex": 68
      },
      {
        "entityName": "str_date",
        "startCharIndex": 106,
        "endCharIndex": 109
      }
    ]
  },
  {
    "text": "no",
    "intentName": "None",
    "entityLabels": []
  },
  {
    "text": "Where else could I go?",
    "intentName": "None",
    "entityLabels": []
  },
  {
    "text": "Anywhere else?",
    "intentName": "None",
    "entityLabels": []
  },
  {
    "text": "Anywhere else?",
    "intentName": "None",
    "entityLabels": []
  },
  {
    "text": "is that all the options?",
    "intentName": "None",
    "entityLabels": [
      {
        "entityName": "dst_city",
        "startCharIndex": 8,
        "endCharIndex": 11
      }
    ]
  },
  {
    "text": "okay. Well what is the best package for Seattle?",
    "intentName": "None",
    "entityLabels": [
      {
        "entityName": "dst_city",
        "startCharIndex": 40,
        "endCharIndex": 47
      }
    ]
  },
  {
    "text": "i like it, when are the flights?",
    "intentName": "None",
    "entityLabels": []
  },
  {
    "text": "that sounds good to me. Book me this one.",
    "intentName": "book",
    "entityLabels": []
  },
  {
    "text": "thanks!",
    "intentName": "None",
    "entityLabels": []
  },
  {
    "text": "Hi there",
    "intentName": "None",
    "entityLabels": []
  },
  {
    "text": "Looking to go from Melbourne to Paris. Have 2600 to spend on tickets for 9 adults",
    "intentName": "None",
    "entityLabels": [
      {
        "entityName": "or_city",
        "startCharIndex": 19,
        "endCharIndex": 28
      },
      {
        "entityName": "dst_city",
        "startCharIndex": 32,
        "endCharIndex": 37
      },
      {
        "entityName": "budget",
        "startCharIndex": 44,
        "endCharIndex": 48
      }
    ]
  },
  {
    "text": "Do you do Paris to Melbourne?",
    "intentName": "None",
    "entityLabels": [
      {
        "entityName": "or_city",
        "startCharIndex": 10,
        "endCharIndex": 15
      },
      {
        "entityName": "dst_city",
        "startCharIndex": 19,
        "endCharIndex": 28
      }
    ]
  },
  {
    "text": "what about paris to tel aviv, same conditions",
    "intentName": "None",
    "entityLabels": [
      {
        "entityName": "or_city",
        "startCharIndex": 11,
        "endCharIndex": 16
      },
      {
        "entityName": "dst_city",
        "startCharIndex": 20,
        "endCharIndex": 28
      }
    ]
  },
  {
    "text": "I want to find a vacation between September 12th and 18th to San Diego from Calgary for under 1800.",
    "intentName": "book",
    "entityLabels": [
      {
        "entityName": "str_date",
        "startCharIndex": 34,
        "endCharIndex": 48
      },
      {
        "entityName": "end_date",
        "startCharIndex": 53,
        "endCharIndex": 57
      },
      {
        "entityName": "dst_city",
        "startCharIndex": 61,
        "endCharIndex": 70
      },
      {
        "entityName": "or_city",
        "startCharIndex": 76,
        "endCharIndex": 83
      },
      {
        "entityName": "budget",
        "startCharIndex": 94,
        "endCharIndex": 98
      }
    ]
  },
  {
    "text": "just me myself and i",
    "intentName": "None",
    "entityLabels": []
  },
  {
    "text": "whats the hotel rated?",
    "intentName": "None",
    "entityLabels": []
  },
  {
    "text": "Is there a hotel with a higher rating?",
    "intentName": "None",
    "entityLabels": []
  },
  {
    "text": "okay, thats fine. Go ahead and book it for me then, i just wanna get away.",
    "intentName": "book",
    "entityLabels": []
  },
  {
    "text": "yeah thats fine",
    "intentName": "None",
    "entityLabels": []
  },
  {
    "text": "Thanks",
    "intentName": "None",
    "entityLabels": []
  },
  {
    "text": "I want to find a vacay between sept.12 and 19 for under 5500, leaving from Mannheim",
    "intentName": "book",
    "entityLabels": [
      {
        "entityName": "str_date",
        "startCharIndex": 31,
        "endCharIndex": 38
      },
      {
        "entityName": "end_date",
        "startCharIndex": 43,
        "endCharIndex": 45
      },
      {
        "entityName": "budget",
        "startCharIndex": 56,
        "endCharIndex": 60
      },
      {
        "entityName": "or_city",
        "startCharIndex": 75,
        "endCharIndex": 83
      }
    ]
  },
  {
    "text": "Nope",
    "intentName": "None",
    "entityLabels": []
  },
  {
    "text": "yeppers, all by my lonesome",
    "intentName": "None",
    "entityLabels": []
  },
  {
    "text": "Can you give me some info on Cordoba",
    "intentName": "None",
    "entityLabels": [
      {
        "entityName": "dst_city",
        "startCharIndex": 29,
        "endCharIndex": 36
      }
    ]
  },
  {
    "text": "Wow! That's lucky! I think i'll end up going with this package but before I make up my mind can you check packages to Paris?",
    "intentName": "None",
    "entityLabels": [
      {
        "entityName": "dst_city",
        "startCharIndex": 118,
        "endCharIndex": 123
      }
    ]
  },
  {
    "text": "pass, what about Hiroshima",
    "intentName": "None",
    "entityLabels": [
      {
        "entityName": "dst_city",
        "startCharIndex": 17,
        "endCharIndex": 26
      }
    ]
  },
  {
    "text": "nope, im deinintely goin with the 5 star hotel. hook me up",
    "intentName": "book",
    "entityLabels": []
  },
  {
    "text": "thanks",
    "intentName": "None",
    "entityLabels": []
  },
  {
    "text": "I would like to go to Nagoya please :slightly_smiling_face:",
    "intentName": "book",
    "entityLabels": [
      {
        "entityName": "dst_city",
        "startCharIndex": 22,
        "endCharIndex": 28
      }
    ]
  },
  {
    "text": "Busan",
    "intentName": "None",
    "entityLabels": [
      {
        "entityName": "or_city",
        "startCharIndex": 0,
        "endCharIndex": 5
      }
    ]
  },
  {
    "text": "september 7-21 and i have a tight budget of 3800",
    "intentName": "None",
    "entityLabels": [
      {
        "entityName": "str_date",
        "startCharIndex": 0,
        "endCharIndex": 11
      },
      {
        "entityName": "end_date",
        "startCharIndex": 12,
        "endCharIndex": 14
      },
      {
        "entityName": "budget",
        "startCharIndex": 44,
        "endCharIndex": 48
      }
    ]
  },
  {
    "text": "what\u2019s the best package you have for Leon?",
    "intentName": "None",
    "entityLabels": [
      {
        "entityName": "dst_city",
        "startCharIndex": 37,
        "endCharIndex": 41
      }
    ]
  },
  {
    "text": "oo baby, now we\u2019re cookin\u2019. Do you have any packages to Paris?",
    "intentName": "None",
    "entityLabels": [
      {
        "entityName": "dst_city",
        "startCharIndex": 56,
        "endCharIndex": 61
      }
    ]
  },
  {
    "text": "Okay, How much does the longer package at the 5 star hotel in leon cost?",
    "intentName": "None",
    "entityLabels": [
      {
        "entityName": "dst_city",
        "startCharIndex": 62,
        "endCharIndex": 66
      }
    ]
  },
  {
    "text": "I\u2019ll take it please",
    "intentName": "book",
    "entityLabels": []
  },
  {
    "text": "Thank you!",
    "intentName": "None",
    "entityLabels": []
  },
  {
    "text": "do you have flights out of tel aviv??",
    "intentName": "book",
    "entityLabels": [
      {
        "entityName": "or_city",
        "startCharIndex": 27,
        "endCharIndex": 35
      }
    ]
  },
  {
    "text": "what about Beijing",
    "intentName": "None",
    "entityLabels": [
      {
        "entityName": "or_city",
        "startCharIndex": 11,
        "endCharIndex": 18
      }
    ]
  },
  {
    "text": "San Jose to Porto Alegre please. oh it needs to be between sept 18 to 22",
    "intentName": "book",
    "entityLabels": [
      {
        "entityName": "or_city",
        "startCharIndex": 0,
        "endCharIndex": 8
      },
      {
        "entityName": "dst_city",
        "startCharIndex": 12,
        "endCharIndex": 24
      },
      {
        "entityName": "str_date",
        "startCharIndex": 59,
        "endCharIndex": 66
      },
      {
        "entityName": "end_date",
        "startCharIndex": 70,
        "endCharIndex": 72
      }
    ]
  },
  {
    "text": "please get me from Jerusalem to Sydney",
    "intentName": "book",
    "entityLabels": [
      {
        "entityName": "or_city",
        "startCharIndex": 19,
        "endCharIndex": 28
      },
      {
        "entityName": "dst_city",
        "startCharIndex": 32,
        "endCharIndex": 38
      }
    ]
  },
  {
    "text": "do you do Beijing flights to Sydney??",
    "intentName": "None",
    "entityLabels": [
      {
        "entityName": "or_city",
        "startCharIndex": 10,
        "endCharIndex": 17
      },
      {
        "entityName": "dst_city",
        "startCharIndex": 29,
        "endCharIndex": 35
      }
    ]
  },
  {
    "text": "I want to go to brasilia from birmingham",
    "intentName": "book",
    "entityLabels": [
      {
        "entityName": "dst_city",
        "startCharIndex": 16,
        "endCharIndex": 24
      },
      {
        "entityName": "or_city",
        "startCharIndex": 30,
        "endCharIndex": 40
      }
    ]
  },
  {
    "text": "i have 1600",
    "intentName": "None",
    "entityLabels": [
      {
        "entityName": "budget",
        "startCharIndex": 7,
        "endCharIndex": 11
      }
    ]
  },
  {
    "text": "doesnt matter, i cant book anything, im a lowlife and can only dream",
    "intentName": "None",
    "entityLabels": []
  },
  {
    "text": "i like. How about trips to Belo Horizonte",
    "intentName": "None",
    "entityLabels": [
      {
        "entityName": "dst_city",
        "startCharIndex": 27,
        "endCharIndex": 41
      }
    ]
  },
  {
    "text": "any trips to houst?",
    "intentName": "None",
    "entityLabels": [
      {
        "entityName": "dst_city",
        "startCharIndex": 13,
        "endCharIndex": 18
      }
    ]
  },
  {
    "text": "I want to go to Dublin",
    "intentName": "book",
    "entityLabels": [
      {
        "entityName": "dst_city",
        "startCharIndex": 16,
        "endCharIndex": 22
      }
    ]
  },
  {
    "text": "cancun and from september 11 to 28 or somewhere around there",
    "intentName": "None",
    "entityLabels": [
      {
        "entityName": "or_city",
        "startCharIndex": 0,
        "endCharIndex": 6
      },
      {
        "entityName": "str_date",
        "startCharIndex": 16,
        "endCharIndex": 28
      },
      {
        "entityName": "end_date",
        "startCharIndex": 32,
        "endCharIndex": 34
      }
    ]
  },
  {
    "text": "what is the highest rated hotel",
    "intentName": "None",
    "entityLabels": []
  },
  {
    "text": "ew. Any trips to kochi?",
    "intentName": "None",
    "entityLabels": [
      {
        "entityName": "dst_city",
        "startCharIndex": 17,
        "endCharIndex": 22
      }
    ]
  },
  {
    "text": "what if i leave from Recife",
    "intentName": "None",
    "entityLabels": [
      {
        "entityName": "or_city",
        "startCharIndex": 21,
        "endCharIndex": 27
      }
    ]
  },
  {
    "text": "What about from Recife to Dublin",
    "intentName": "None",
    "entityLabels": [
      {
        "entityName": "or_city",
        "startCharIndex": 16,
        "endCharIndex": 22
      },
      {
        "entityName": "dst_city",
        "startCharIndex": 26,
        "endCharIndex": 32
      }
    ]
  },
  {
    "text": "Is there anything to Buenos Aires",
    "intentName": "None",
    "entityLabels": [
      {
        "entityName": "dst_city",
        "startCharIndex": 21,
        "endCharIndex": 33
      }
    ]
  },
  {
    "text": "ok is the 3.5 star hotel near anything interesting?",
    "intentName": "None",
    "entityLabels": []
  },
  {
    "text": "cool beanie weenies. Book it for me and 3 of my friends",
    "intentName": "book",
    "entityLabels": []
  },
  {
    "text": "i like it. can you book it for me please",
    "intentName": "book",
    "entityLabels": []
  },
  {
    "text": "yes",
    "intentName": "None",
    "entityLabels": []
  },
  {
    "text": "Thanks",
    "intentName": "None",
    "entityLabels": []
  },
  {
    "text": "Hello there. I am the father of a group of 4 spoiled, privileged brats\nI've decided to book them a trip to see how those in less fortunate parts of the world live\nGive them some perspective, you know?\nSee if you can get me, my wife, and the four kids to Guadalajara, from Calgary",
    "intentName": "None",
    "entityLabels": [
      {
        "entityName": "dst_city",
        "startCharIndex": 254,
        "endCharIndex": 265
      },
      {
        "entityName": "or_city",
        "startCharIndex": 272,
        "endCharIndex": 279
      }
    ]
  },
  {
    "text": "2 and 4",
    "intentName": "None",
    "entityLabels": []
  },
  {
    "text": "I suppose we _could_ take them to Rio de Janeiro also",
    "intentName": "None",
    "entityLabels": [
      {
        "entityName": "dst_city",
        "startCharIndex": 34,
        "endCharIndex": 48
      }
    ]
  },
  {
    "text": "Do you think I could still get the message across if we went to San Juan?",
    "intentName": "None",
    "entityLabels": [
      {
        "entityName": "dst_city",
        "startCharIndex": 64,
        "endCharIndex": 72
      }
    ]
  },
  {
    "text": "That is not an option",
    "intentName": "None",
    "entityLabels": []
  },
  {
    "text": "I have 0 budget, 16 days vacay, leaving from barcelona and am looking for possible destinations",
    "intentName": "book",
    "entityLabels": [
      {
        "entityName": "budget",
        "startCharIndex": 7,
        "endCharIndex": 8
      },
      {
        "entityName": "or_city",
        "startCharIndex": 45,
        "endCharIndex": 54
      }
    ]
  },
  {
    "text": "ughhhh fine, i guess i can up it to 400",
    "intentName": "None",
    "entityLabels": [
      {
        "entityName": "budget",
        "startCharIndex": 36,
        "endCharIndex": 39
      }
    ]
  },
  {
    "text": "well give me more info and ill let you know",
    "intentName": "None",
    "entityLabels": []
  },
  {
    "text": "are there any other options",
    "intentName": "None",
    "entityLabels": []
  },
  {
    "text": "what is it rated",
    "intentName": "None",
    "entityLabels": []
  },
  {
    "text": "does it offer anything",
    "intentName": "None",
    "entityLabels": []
  },
  {
    "text": "does it have free wifi or anything like that",
    "intentName": "None",
    "entityLabels": []
  },
  {
    "text": "is it near a mall",
    "intentName": "None",
    "entityLabels": []
  },
  {
    "text": "I think i will book this one. is there a business flight for it?",
    "intentName": "None",
    "entityLabels": []
  },
  {
    "text": "yeah ill do that",
    "intentName": "None",
    "entityLabels": []
  },
  {
    "text": "thanks!",
    "intentName": "None",
    "entityLabels": []
  },
  {
    "text": "hello!",
    "intentName": "book",
    "entityLabels": []
  },
  {
    "text": "i have between september 6 to 21 to take my team somewhere nice. can you please book six adults from nagoya to buenos aires",
    "intentName": "None",
    "entityLabels": [
      {
        "entityName": "str_date",
        "startCharIndex": 15,
        "endCharIndex": 26
      },
      {
        "entityName": "end_date",
        "startCharIndex": 30,
        "endCharIndex": 32
      },
      {
        "entityName": "or_city",
        "startCharIndex": 101,
        "endCharIndex": 107
      },
      {
        "entityName": "dst_city",
        "startCharIndex": 111,
        "endCharIndex": 123
      }
    ]
  },
  {
    "text": "yes",
    "intentName": "None",
    "entityLabels": []
  },
  {
    "text": "no budget!",
    "intentName": "None",
    "entityLabels": []
  }
]