[
  {
    "text": "Alright I'll still leave from Osaka! Please finalize this deal for me!",
    "intentName": "book",
    "entityLabels": [
      {
        "entityName": "or_city",
        "startCharIndex": 30,
        "endCharIndex": 35
      }
    ]
  },
  {
    "text": "Awesome. Thanks so much!",
    "intentName": "None",
    "entityLabels": []
  },
  {
    "text": "I want to go to Guadalajara with my home girlz.",
    "intentName": "book",
    "entityLabels": [
      {
        "entityName": "dst_city",
        "startCharIndex": 16,
        "endCharIndex": 27
      }
    ]
  },
  {
    "text": "7 And Seattle",
    "intentName": "None",
    "entityLabels": [
      {
        "entityName": "or_city",
        "startCharIndex": 6,
        "endCharIndex": 13
      }
    ]
  },
  {
    "text": "Seattle",
    "intentName": "None",
    "entityLabels": [
      {
        "entityName": "or_city",
        "startCharIndex": 0,
        "endCharIndex": 7
      }
    ]
  },
  {
    "text": "5 stars for sure. We want the best package.",
    "intentName": "None",
    "entityLabels": []
  },
  {
    "text": "No I need 5 stars. Check Kobe",
    "intentName": "None",
    "entityLabels": [
      {
        "entityName": "dst_city",
        "startCharIndex": 25,
        "endCharIndex": 29
      }
    ]
  },
  {
    "text": "Sure, tell me about it.",
    "intentName": "None",
    "entityLabels": []
  },
  {
    "text": "Anything in Ulsan?",
    "intentName": "None",
    "entityLabels": [
      {
        "entityName": "dst_city",
        "startCharIndex": 12,
        "endCharIndex": 17
      }
    ]
  },
  {
    "text": "Which hotel has a higher guest rating?",
    "intentName": "None",
    "entityLabels": []
  },
  {
    "text": "Do one of the hotels have a spa?",
    "intentName": "None",
    "entityLabels": []
  },
  {
    "text": "Well we really love to shop but the other hotel has a better guest rating. I think we will just go to the Escape Cave anyway. Book it, business class.",
    "intentName": "book",
    "entityLabels": []
  },
  {
    "text": "Thanks",
    "intentName": "None",
    "entityLabels": []
  },
  {
    "text": "I need to get home on or after September 8th!",
    "intentName": "book",
    "entityLabels": [
      {
        "entityName": "str_date",
        "startCharIndex": 31,
        "endCharIndex": 44
      }
    ]
  },
  {
    "text": "I need to go to Belem from Stuttgart!",
    "intentName": "None",
    "entityLabels": [
      {
        "entityName": "dst_city",
        "startCharIndex": 16,
        "endCharIndex": 21
      },
      {
        "entityName": "or_city",
        "startCharIndex": 27,
        "endCharIndex": 36
      }
    ]
  },
  {
    "text": "yes and I have 4000",
    "intentName": "None",
    "entityLabels": [
      {
        "entityName": "budget",
        "startCharIndex": 15,
        "endCharIndex": 19
      }
    ]
  },
  {
    "text": "as long as I can, its a family emergency",
    "intentName": "None",
    "entityLabels": []
  },
  {
    "text": "yes! Please book me the economy package!",
    "intentName": "None",
    "entityLabels": []
  },
  {
    "text": "Thank you!",
    "intentName": "None",
    "entityLabels": []
  },
  {
    "text": "We must go to Atlanta!",
    "intentName": "book",
    "entityLabels": [
      {
        "entityName": "dst_city",
        "startCharIndex": 14,
        "endCharIndex": 21
      }
    ]
  },
  {
    "text": "San Juan.",
    "intentName": "None",
    "entityLabels": [
      {
        "entityName": "or_city",
        "startCharIndex": 0,
        "endCharIndex": 8
      }
    ]
  },
  {
    "text": "7 full size and 3 mini size",
    "intentName": "None",
    "entityLabels": []
  },
  {
    "text": "Can you show me the best packages you've got? Although keep it under 21100 please.",
    "intentName": "None",
    "entityLabels": [
      {
        "entityName": "budget",
        "startCharIndex": 69,
        "endCharIndex": 74
      }
    ]
  },
  {
    "text": "And how did previous guests like it?",
    "intentName": "None",
    "entityLabels": []
  },
  {
    "text": "How's the other hotel?",
    "intentName": "None",
    "entityLabels": []
  },
  {
    "text": "Can you tell me more about the 8.37/10 one?",
    "intentName": "None",
    "entityLabels": []
  },
  {
    "text": "Will any other packages show up if I increase my budget by 1500?",
    "intentName": "None",
    "entityLabels": [
      {
        "entityName": "budget",
        "startCharIndex": 37,
        "endCharIndex": 63
      }
    ]
  },
  {
    "text": "You know what, I will take the 3.5 star then. Are business flights available?",
    "intentName": "None",
    "entityLabels": []
  },
  {
    "text": "Okay let's book it!",
    "intentName": "book",
    "entityLabels": []
  },
  {
    "text": "Thanks!",
    "intentName": "None",
    "entityLabels": []
  },
  {
    "text": "I need to get to Fortaleza from Paris. We will be 2 adults and 7 children",
    "intentName": "book",
    "entityLabels": [
      {
        "entityName": "dst_city",
        "startCharIndex": 17,
        "endCharIndex": 26
      },
      {
        "entityName": "or_city",
        "startCharIndex": 32,
        "endCharIndex": 37
      }
    ]
  },
  {
    "text": "19500",
    "intentName": "None",
    "entityLabels": [
      {
        "entityName": "budget",
        "startCharIndex": 0,
        "endCharIndex": 5
      }
    ]
  },
  {
    "text": "Possibly. What is the hotel like?",
    "intentName": "None",
    "entityLabels": []
  },
  {
    "text": "yes that is perfect. Could you book this for me?",
    "intentName": "book",
    "entityLabels": []
  },
  {
    "text": "THANK YOU!",
    "intentName": "None",
    "entityLabels": []
  },
  {
    "text": "Gotta go to Hamburg. In Puebla now",
    "intentName": "book",
    "entityLabels": [
      {
        "entityName": "dst_city",
        "startCharIndex": 12,
        "endCharIndex": 19
      },
      {
        "entityName": "or_city",
        "startCharIndex": 24,
        "endCharIndex": 30
      }
    ]
  },
  {
    "text": "Dates and budget don't matter just find me something",
    "intentName": "None",
    "entityLabels": []
  },
  {
    "text": "Yup",
    "intentName": "None",
    "entityLabels": []
  },
  {
    "text": "Is that also the highest star-rated hotel you've got?",
    "intentName": "None",
    "entityLabels": []
  },
  {
    "text": "Where is this hotel located?",
    "intentName": "None",
    "entityLabels": []
  },
  {
    "text": "Got any amenities?",
    "intentName": "None",
    "entityLabels": []
  },
  {
    "text": "Can you get me into business class?",
    "intentName": "None",
    "entityLabels": []
  },
  {
    "text": "Only if you ca get me into biz",
    "intentName": "None",
    "entityLabels": []
  },
  {
    "text": "Sounds good to me",
    "intentName": "None",
    "entityLabels": []
  },
  {
    "text": "Thx!",
    "intentName": "None",
    "entityLabels": []
  },
  {
    "text": "I NEED TO GET TO SAN ANTONIO FROM TAMPA",
    "intentName": "book",
    "entityLabels": [
      {
        "entityName": "dst_city",
        "startCharIndex": 17,
        "endCharIndex": 28
      },
      {
        "entityName": "or_city",
        "startCharIndex": 34,
        "endCharIndex": 39
      }
    ]
  },
  {
    "text": "September 26",
    "intentName": "None",
    "entityLabels": [
      {
        "entityName": "str_date",
        "startCharIndex": 0,
        "endCharIndex": 12
      }
    ]
  },
  {
    "text": "NO I NEED TO LEAVE FROM TAMPA",
    "intentName": "None",
    "entityLabels": [
      {
        "entityName": "or_city",
        "startCharIndex": 24,
        "endCharIndex": 29
      }
    ]
  },
  {
    "text": "OKAY. WHAT IS THE HOTEL LIKE?",
    "intentName": "None",
    "entityLabels": []
  },
  {
    "text": "NICE.  DO YOU HAVE ANYTHING IN ATLANTA?",
    "intentName": "None",
    "entityLabels": [
      {
        "entityName": "dst_city",
        "startCharIndex": 31,
        "endCharIndex": 38
      }
    ]
  },
  {
    "text": "YA",
    "intentName": "None",
    "entityLabels": []
  },
  {
    "text": "I WANT TO BOOK THE OTHER PACKAGE! MUST FIND MEWTWO!",
    "intentName": "None",
    "entityLabels": []
  },
  {
    "text": "THERES 7 OF US",
    "intentName": "None",
    "entityLabels": []
  },
  {
    "text": "yeah. Lets book it",
    "intentName": "book",
    "entityLabels": []
  },
  {
    "text": "thanks",
    "intentName": "None",
    "entityLabels": []
  },
  {
    "text": "Hey bot. I got all the money there is in the world\nFind me the best okay?",
    "intentName": "book",
    "entityLabels": []
  },
  {
    "text": "Lima should have some good stuff. My bestie and I are in St. Petersburg right now\nOh yeah we also need to be back by the 25th keep that in mind",
    "intentName": "None",
    "entityLabels": [
      {
        "entityName": "dst_city",
        "startCharIndex": 0,
        "endCharIndex": 4
      },
      {
        "entityName": "or_city",
        "startCharIndex": 57,
        "endCharIndex": 71
      },
      {
        "entityName": "end_date",
        "startCharIndex": 121,
        "endCharIndex": 125
      }
    ]
  },
  {
    "text": "4 star? That's the best you have?",
    "intentName": "None",
    "entityLabels": []
  },
  {
    "text": "Find me a 5 star in Punta Cana",
    "intentName": "None",
    "entityLabels": [
      {
        "entityName": "dst_city",
        "startCharIndex": 20,
        "endCharIndex": 30
      }
    ]
  },
  {
    "text": "I can also leave from Curitiba, Can you find any better hotels in Lima in this case?",
    "intentName": "None",
    "entityLabels": [
      {
        "entityName": "or_city",
        "startCharIndex": 22,
        "endCharIndex": 30
      },
      {
        "entityName": "dst_city",
        "startCharIndex": 66,
        "endCharIndex": 70
      }
    ]
  },
  {
    "text": "No. I'd rather have the 4 star. Is the 4 star close to the beach at least?",
    "intentName": "None",
    "entityLabels": []
  },
  {
    "text": "Yeah let's do that with business seats",
    "intentName": "None",
    "entityLabels": []
  },
  {
    "text": "Okay thanks!",
    "intentName": "None",
    "entityLabels": []
  },
  {
    "text": "I NEED TO GET OUT OF NORTH VANCOUVER ON SEPTEMBER 8TH. CAN I GET A FLIGHT TO DUBLIN?",
    "intentName": "book",
    "entityLabels": [
      {
        "entityName": "or_city",
        "startCharIndex": 21,
        "endCharIndex": 36
      },
      {
        "entityName": "str_date",
        "startCharIndex": 40,
        "endCharIndex": 53
      },
      {
        "entityName": "dst_city",
        "startCharIndex": 77,
        "endCharIndex": 83
      }
    ]
  },
  {
    "text": "NO I NEED TO LEAVE ON THE 8TH.",
    "intentName": "None",
    "entityLabels": [
      {
        "entityName": "str_date",
        "startCharIndex": 26,
        "endCharIndex": 29
      }
    ]
  },
  {
    "text": "NO I NEED TO LEAVE ON THE 8TH. DO YOU HAVE ANYTHING LEAVING FROM CLEVELAND",
    "intentName": "None",
    "entityLabels": [
      {
        "entityName": "str_date",
        "startCharIndex": 26,
        "endCharIndex": 29
      },
      {
        "entityName": "or_city",
        "startCharIndex": 65,
        "endCharIndex": 74
      }
    ]
  },
  {
    "text": "NO BUT I CAN GO TO SACRAMENTO",
    "intentName": "None",
    "entityLabels": [
      {
        "entityName": "dst_city",
        "startCharIndex": 19,
        "endCharIndex": 29
      }
    ]
  },
  {
    "text": "I want to get to Paris from Cordoba",
    "intentName": "book",
    "entityLabels": [
      {
        "entityName": "dst_city",
        "startCharIndex": 17,
        "endCharIndex": 22
      },
      {
        "entityName": "or_city",
        "startCharIndex": 28,
        "endCharIndex": 35
      }
    ]
  },
  {
    "text": "1 kid and 4 adults for 3300",
    "intentName": "None",
    "entityLabels": [
      {
        "entityName": "budget",
        "startCharIndex": 23,
        "endCharIndex": 27
      }
    ]
  },
  {
    "text": "13",
    "intentName": "None",
    "entityLabels": []
  },
  {
    "text": "yes!",
    "intentName": "None",
    "entityLabels": []
  },
  {
    "text": "Thanks!",
    "intentName": "None",
    "entityLabels": []
  },
  {
    "text": "Hey there! The 17 of us wants to get out of Tel Aviv for a sweet trip.",
    "intentName": "None",
    "entityLabels": [
      {
        "entityName": "or_city",
        "startCharIndex": 44,
        "endCharIndex": 52
      }
    ]
  },
  {
    "text": "I can pay as much as needed!",
    "intentName": "None",
    "entityLabels": []
  },
  {
    "text": "I have 8 days vacation",
    "intentName": "book",
    "entityLabels": []
  },
  {
    "text": "from frankfurt and i dont know where i wanna go but i want to leave on or after the 18th",
    "intentName": "None",
    "entityLabels": [
      {
        "entityName": "or_city",
        "startCharIndex": 5,
        "endCharIndex": 14
      },
      {
        "entityName": "str_date",
        "startCharIndex": 84,
        "endCharIndex": 88
      }
    ]
  },
  {
    "text": "no.",
    "intentName": "None",
    "entityLabels": []
  },
  {
    "text": "8",
    "intentName": "None",
    "entityLabels": []
  },
  {
    "text": "Yes that sounds pretty good. Can you tell me more?",
    "intentName": "None",
    "entityLabels": []
  },
  {
    "text": "Ok. Do you have any better hotels?",
    "intentName": "None",
    "entityLabels": []
  },
  {
    "text": "yeah tell me more",
    "intentName": "None",
    "entityLabels": []
  },
  {
    "text": "Sure! This one seems to be more what I\u2019m looking for. Is the hotel near anything?",
    "intentName": "None",
    "entityLabels": []
  },
  {
    "text": "business for sure",
    "intentName": "None",
    "entityLabels": []
  },
  {
    "text": "Thanks so much",
    "intentName": "None",
    "entityLabels": []
  },
  {
    "text": "I'd like to go to Washington.",
    "intentName": "book",
    "entityLabels": [
      {
        "entityName": "dst_city",
        "startCharIndex": 18,
        "endCharIndex": 28
      }
    ]
  },
  {
    "text": "Naples",
    "intentName": "None",
    "entityLabels": [
      {
        "entityName": "or_city",
        "startCharIndex": 0,
        "endCharIndex": 6
      }
    ]
  },
  {
    "text": "I also had Sao Paulo in my mind..",
    "intentName": "None",
    "entityLabels": [
      {
        "entityName": "dst_city",
        "startCharIndex": 11,
        "endCharIndex": 20
      }
    ]
  },
  {
    "text": "The 3 star would be great if it's under my budget of 5600..",
    "intentName": "None",
    "entityLabels": [
      {
        "entityName": "budget",
        "startCharIndex": 53,
        "endCharIndex": 57
      }
    ]
  },
  {
    "text": "Great let's book it!",
    "intentName": "book",
    "entityLabels": []
  },
  {
    "text": "Thanks!",
    "intentName": "None",
    "entityLabels": []
  },
  {
    "text": "I would like to find a great package from Birmingham to Porto for 6 days.",
    "intentName": "book",
    "entityLabels": [
      {
        "entityName": "or_city",
        "startCharIndex": 42,
        "endCharIndex": 52
      },
      {
        "entityName": "dst_city",
        "startCharIndex": 56,
        "endCharIndex": 61
      }
    ]
  },
  {
    "text": "How about to Naples instead?",
    "intentName": "None",
    "entityLabels": [
      {
        "entityName": "dst_city",
        "startCharIndex": 13,
        "endCharIndex": 19
      }
    ]
  },
  {
    "text": "I want to go to Leon from Nagoya between the 13th and october 2nd.",
    "intentName": "book",
    "entityLabels": [
      {
        "entityName": "dst_city",
        "startCharIndex": 16,
        "endCharIndex": 20
      },
      {
        "entityName": "or_city",
        "startCharIndex": 26,
        "endCharIndex": 32
      },
      {
        "entityName": "str_date",
        "startCharIndex": 45,
        "endCharIndex": 49
      },
      {
        "entityName": "end_date",
        "startCharIndex": 54,
        "endCharIndex": 65
      }
    ]
  },
  {
    "text": "no",
    "intentName": "None",
    "entityLabels": []
  },
  {
    "text": "That sounds amazing. Before I make up my mind can you check a few other places for me? I was thinking about Boston.",
    "intentName": "None",
    "entityLabels": [
      {
        "entityName": "dst_city",
        "startCharIndex": 108,
        "endCharIndex": 114
      }
    ]
  },
  {
    "text": "Tell me more about the 3 star hotel.",
    "intentName": "None",
    "entityLabels": []
  },
  {
    "text": "Not bad. Can you check packages to Sapporo?",
    "intentName": "None",
    "entityLabels": [
      {
        "entityName": "dst_city",
        "startCharIndex": 35,
        "endCharIndex": 42
      }
    ]
  },
  {
    "text": "Tell me more",
    "intentName": "None",
    "entityLabels": []
  },
  {
    "text": "Great! One more place i'd like to know about is Hamburg.",
    "intentName": "None",
    "entityLabels": [
      {
        "entityName": "dst_city",
        "startCharIndex": 48,
        "endCharIndex": 55
      }
    ]
  },
  {
    "text": "can I hear about the 4.5 star",
    "intentName": "None",
    "entityLabels": []
  }
]